src/cli.py
src/canify/__init__.py
src/canify/decorators.py
src/canify/types.py
src/canify/daemon/__init__.py
src/canify/daemon/core.py
src/canify/daemon/file_watcher.py
src/canify/discovery/spec_discoverer.py
src/canify/execution/spec_executor.py
src/canify/extraction/spec_extractor.py
src/canify/filtering/__init__.py
src/canify/filtering/tag_filter.py
src/canify/ipc/__init__.py
src/canify/ipc/client.py
src/canify/ipc/protocol.py
src/canify/ipc/server.py
src/canify/models/__init__.py
src/canify/models/entity_declaration.py
src/canify/models/entity_reference.py
src/canify/models/location.py
src/canify/models/spec.py
src/canify/models/validation_result.py
src/canify/models/view.py
src/canify/parsers/__init__.py
src/canify/parsers/entity_declaration_parser.py
src/canify/parsers/entity_field_reference_parser.py
src/canify/parsers/entity_reference_parser.py
src/canify/parsers/entity_schema_parser.py
src/canify/parsers/spec_parser.py
src/canify/parsers/symbol_extractor.py
src/canify/storage/__init__.py
src/canify/storage/database.py
src/canify/storage/spec_storage.py
src/canify/storage/symbol_table.py
src/canify/validation/__init__.py
src/canify/validation/reference_validator.py
src/canify/validation/schema_validator.py
src/canify/validation/spec_validator.py
src/canify/validation/type_constraint_validator.py
src/canify/validation/validation_engine.py
src/client/__init__.py
src/client/daemon_client.py
src/commands/__init__.py
src/commands/daemon.py
src/commands/version.py
canify-0.1.0.dist-info/METADATA
canify-0.1.0.dist-info/WHEEL
canify-0.1.0.dist-info/entry_points.txt
canify-0.1.0.dist-info/RECORD
